mobility_virtual_environment-0.14.3.data/scripts/killall_vehicle_models.sh
mobility_virtual_environment-0.14.3.data/scripts/run_move_dashboard.sh
mobility_virtual_environment-0.14.3.data/scripts/run_move_live_mapping.sh
mobility_virtual_environment-0.14.3.data/scripts/test_parallel_ssh_with_screen.py
mobility_virtual_environment-0.14.3.data/scripts/test_python_packages.py
move/core/__init__.py
move/core/all_vehicles.py
move/core/core_udp_io.py
move/core/main_changeRunState.py
move/core/main_core.py
move/core/main_launch_veh_process.py
move/core/sync_function.py
move/data_displays/__init__.py
move/data_displays/move_dashboard.py
move/data_displays/move_live_mapping.py
move/data_displays/icons/aerial_fixedwing_32x32.png
move/data_displays/icons/aerial_fixedwing_grn_32x32.png
move/data_displays/icons/aerial_fixedwing_red_32x32.png
move/data_displays/icons/aerial_quad_32x32_arrow.png
move/data_displays/icons/ground_indy_car_blue_32x32.png
move/data_displays/icons/ground_indy_car_green_32x32.png
move/data_displays/icons/ground_indy_car_red_32x32.png
move/data_displays/icons/ground_indy_car_yellow_32x32.png
move/data_displays/icons/ground_passenger_car_black_32x32.png
move/data_displays/icons/ground_passenger_car_blue_32x32.png
move/data_displays/icons/ground_passenger_car_cyan_32x32.png
move/data_displays/icons/ground_passenger_car_green_32x32.png
move/data_displays/icons/ground_passenger_car_orange_32x32.png
move/data_displays/icons/ground_passenger_car_red_32x32.png
move/data_displays/icons/ground_truck_armygreen_32x32.png
move/data_displays/icons/ground_truck_grey_32x32.png
move/data_displays/icons/ped_female1.png
move/data_displays/icons/ped_female1_32x32.png
move/data_displays/icons/ped_male1.png
move/data_displays/icons/ped_male1_32x32.png
move/data_displays/icons/surface_boat_a_32x32.png
move/data_displays/icons/surface_turtle_a_32x32.png
move/routes/__init__.py
move/routes/route_01_waypoints.py
move/routes/route_04_waypoints.py
mobility_virtual_environment-0.14.3.dist-info/COPYING
mobility_virtual_environment-0.14.3.dist-info/LICENSE
mobility_virtual_environment-0.14.3.dist-info/METADATA
mobility_virtual_environment-0.14.3.dist-info/WHEEL
mobility_virtual_environment-0.14.3.dist-info/top_level.txt
mobility_virtual_environment-0.14.3.dist-info/RECORD
