Metadata-Version: 2.1
Name: mobility-virtual-environment
Version: 0.14.3
Summary: The Mobility Virtual Environment (MoVE) tests multi-vehicle mobility scenarios.
Home-page: https://comperem.gitlab.io/move/
Author: Marc Compere
Author-email: comperem@gmail.com
Project-URL: Bug Tracker, https://gitlab.com/comperem/move/issues
Keywords: multi-vehicle,multi-agent,simulation,mobility,v2v
Classifier: Development Status :: 4 - Beta
Classifier: Intended Audience :: Science/Research
Classifier: Topic :: Communications
Classifier: Topic :: Scientific/Engineering
Classifier: Topic :: Scientific/Engineering :: Physics
Classifier: Topic :: Scientific/Engineering :: Visualization
Classifier: Topic :: System :: Networking
Classifier: Programming Language :: Python :: 3
Classifier: Operating System :: POSIX :: Linux
Classifier: License :: OSI Approved :: GNU General Public License v3 (GPLv3)
Requires-Python: >=3.7
License-File: LICENSE
License-File: COPYING
Requires-Dist: wheel
Requires-Dist: screen
Requires-Dist: numpy
Requires-Dist: msgpack
Requires-Dist: msgpack-numpy
Requires-Dist: parallel-ssh
Requires-Dist: utm
Requires-Dist: bokeh
Requires-Dist: imutils
Requires-Dist: matplotlib
Requires-Dist: opencv-python
